setup.cfg
setup.py
cassiopeia_diskstore/__init__.py
cassiopeia_diskstore/champion.py
cassiopeia_diskstore/championgg.py
cassiopeia_diskstore/championmastery.py
cassiopeia_diskstore/common.py
cassiopeia_diskstore/leagues.py
cassiopeia_diskstore/match.py
cassiopeia_diskstore/patch.py
cassiopeia_diskstore/spectator.py
cassiopeia_diskstore/staticdata.py
cassiopeia_diskstore/status.py
cassiopeia_diskstore/summoner.py
cassiopeia_diskstore.egg-info/PKG-INFO
cassiopeia_diskstore.egg-info/SOURCES.txt
cassiopeia_diskstore.egg-info/dependency_links.txt
cassiopeia_diskstore.egg-info/requires.txt
cassiopeia_diskstore.egg-info/top_level.txt
cassiopeia_diskstore.egg-info/zip-safe