Metadata-Version: 1.1
Name: cassiopeia-diskstore
Version: 1.0.6
Summary: A disk data store for the Cassiopeia League of Legends wrapper.
Home-page: https://github.com/meraki-analytics/cassiopeia-datastores/tree/master/cassiopeia-diskstore
Author: Jason Maldonis; Rob Rua
Author-email: team@merakianalytics.com
License: MIT
Platform: UNKNOWN
Classifier: Development Status :: 4 - Beta
Classifier: Programming Language :: Python :: 3
Classifier: Environment :: Web Environment
Classifier: Operating System :: OS Independent
Classifier: Intended Audience :: Developers
Classifier: License :: OSI Approved :: MIT License
